{"stats":{"minecraft:dropped":{"awa_snack:counter":1},"minecraft:picked_up":{"awa_snack:counter":1},"minecraft:custom":{"minecraft:jump":182,"minecraft:time_since_rest":19905,"minecraft:damage_taken":160,"minecraft:play_one_minute":19905,"minecraft:crouch_one_cm":48,"minecraft:leave_game":5,"minecraft:sprint_one_cm":35600,"minecraft:time_since_death":19905,"minecraft:walk_on_water_one_cm":857,"minecraft:walk_one_cm":29134,"minecraft:sneak_time":3,"minecraft:walk_under_water_one_cm":266,"minecraft:swim_one_cm":3347,"minecraft:interact_with_crafting_table":1,"minecraft:fall_one_cm":19557,"minecraft:drop":1,"minecraft:fly_one_cm":73254},"minecraft:used":{"awa_snack:watermelon_pineapple_tea":6,"awa_snack:counter":5,"minecraft:crafting_table":1},"minecraft:crafted":{"awa_snack:watermelon_pineapple_tea":1}},"DataVersion":2586}